drand/__init__.py
drand/constants.py
drand/drand.py
drand/exceptions.py
drand/utils.py
drand-0.1.0.dev3.dist-info/LICENSE
drand-0.1.0.dev3.dist-info/METADATA
drand-0.1.0.dev3.dist-info/WHEEL
drand-0.1.0.dev3.dist-info/top_level.txt
drand-0.1.0.dev3.dist-info/RECORD
