Metadata-Version: 2.1
Name: drand
Version: 0.1.0.dev3
Summary: Python client for drand.
Home-page: https://github.com/initc3/drand.py
Author: Sylvain Bellemare
License: MIT license
Keywords: drand
Platform: UNKNOWN
Classifier: Development Status :: 2 - Pre-Alpha
Classifier: Intended Audience :: Developers
Classifier: License :: OSI Approved :: MIT License
Classifier: Natural Language :: English
Classifier: Programming Language :: Python :: 3
Classifier: Programming Language :: Python :: 3.7
Classifier: Programming Language :: Python :: 3.8
Requires-Python: >=3.6
Requires-Dist: aiohttp
Requires-Dist: py-ecc (~=1.7)
Requires-Dist: toml
Provides-Extra: dev
Requires-Dist: ipdb ; extra == 'dev'
Requires-Dist: ipython ; extra == 'dev'
Requires-Dist: Sphinx ; extra == 'dev'
Requires-Dist: black ; extra == 'dev'
Requires-Dist: coverage ; extra == 'dev'
Requires-Dist: flake8 ; extra == 'dev'
Requires-Dist: flake8-import-order ; extra == 'dev'
Requires-Dist: pep8-naming ; extra == 'dev'
Requires-Dist: pytest ; extra == 'dev'
Requires-Dist: pytest-aiohttp ; extra == 'dev'
Requires-Dist: pytest-cov ; extra == 'dev'
Provides-Extra: docs
Requires-Dist: Sphinx ; extra == 'docs'
Provides-Extra: requests
Requires-Dist: requests ; extra == 'requests'
Provides-Extra: tests
Requires-Dist: black ; extra == 'tests'
Requires-Dist: coverage ; extra == 'tests'
Requires-Dist: flake8 ; extra == 'tests'
Requires-Dist: flake8-import-order ; extra == 'tests'
Requires-Dist: pep8-naming ; extra == 'tests'
Requires-Dist: pytest ; extra == 'tests'
Requires-Dist: pytest-aiohttp ; extra == 'tests'
Requires-Dist: pytest-cov ; extra == 'tests'
